{
  "annotations": {
    "list": [
      {
        "builtIn": 1,
        "datasource": {
          "type": "datasource",
          "uid": "grafana"
        },
        "enable": true,
        "hide": true,
        "iconColor": "rgba(0, 211, 255, 1)",
        "name": "Annotations & Alerts",
        "type": "dashboard"
      }
    ]
  },
  "editable": true,
  "fiscalYearStartMonth": 0,
  "graphTooltip": 0,
  "links": [],
  "panels": [
    {
      "collapsed": false,
      "gridPos": {
        "h": 1,
        "w": 24,
        "x": 0,
        "y": 0
      },
      "id": 9,
      "panels": [],
      "title": "Primary Info",
      "type": "row"
    },
    {
      "datasource": {
        "type": "prometheus",
        "uid": "$PROMETHEUS_DS"
      },
      "fieldConfig": {
        "defaults": {
          "color": {
            "mode": "thresholds"
          },
          "mappings": [
            {
              "options": {
                "match": "null",
                "result": {
                  "text": "N/A"
                }
              },
              "type": "special"
            }
          ],
          "thresholds": {
            "mode": "absolute",
            "steps": [
              {
                "color": "#bf1b00"
              },
              {
                "color": "#629e51",
                "value": 0.99
              },
              {
                "color": "#bf1b00",
                "value": 1.01
              }
            ]
          },
          "unit": "none"
        },
        "overrides": []
      },
      "gridPos": {
        "h": 6,
        "w": 4,
        "x": 0,
        "y": 1
      },
      "id": 1,
      "maxDataPoints": 100,
      "options": {
        "colorMode": "value",
        "graphMode": "area",
        "justifyMode": "auto",
        "orientation": "horizontal",
        "percentChangeColorMode": "standard",
        "reduceOptions": {
          "calcs": [
            "lastNotNull"
          ],
          "fields": "",
          "values": false
        },
        "showPercentChange": false,
        "textMode": "auto",
        "wideLayout": true
      },
      "pluginVersion": "11.6.1",
      "targets": [
        {
          "datasource": {
            "uid": "Global"
          },
          "dsType": "influxdb",
          "editorMode": "code",
          "expr": "count(pg_replication_is_replica{env=\"$environment\"}==0)",
          "format": "time_series",
          "groupBy": [
            {
              "params": [
                "$__interval"
              ],
              "type": "time"
            },
            {
              "params": [
                "null"
              ],
              "type": "fill"
            }
          ],
          "intervalFactor": 2,
          "orderByTime": "ASC",
          "policy": "default",
          "range": true,
          "refId": "A",
          "resultFormat": "time_series",
          "select": [
            [
              {
                "params": [
                  "value"
                ],
                "type": "field"
              },
              {
                "params": [],
                "type": "mean"
              }
            ]
          ],
          "tags": []
        }
      ],
      "title": "Primaries",
      "transparent": true,
      "type": "stat"
    },
    {
      "datasource": {
        "type": "prometheus",
        "uid": "$PROMETHEUS_DS"
      },
      "fieldConfig": {
        "defaults": {
          "color": {
            "mode": "thresholds"
          },
          "custom": {
            "align": "auto",
            "cellOptions": {
              "type": "auto"
            },
            "inspect": false
          },
          "mappings": [],
          "thresholds": {
            "mode": "absolute",
            "steps": [
              {
                "color": "green"
              },
              {
                "color": "red",
                "value": 80
              }
            ]
          }
        },
        "overrides": []
      },
      "gridPos": {
        "h": 6,
        "w": 6,
        "x": 4,
        "y": 1
      },
      "id": 3,
      "options": {
        "cellHeight": "sm",
        "footer": {
          "countRows": false,
          "fields": "",
          "reducer": [
            "sum"
          ],
          "show": false
        },
        "showHeader": true
      },
      "pluginVersion": "11.6.1",
      "targets": [
        {
          "datasource": {
            "uid": "Global"
          },
          "dsType": "influxdb",
          "editorMode": "code",
          "expr": "pg_replication_is_replica{env=\"$environment\"}==0",
          "format": "table",
          "groupBy": [
            {
              "params": [
                "$__interval"
              ],
              "type": "time"
            },
            {
              "params": [
                "null"
              ],
              "type": "fill"
            }
          ],
          "instant": true,
          "interval": "",
          "intervalFactor": 2,
          "legendFormat": "",
          "orderByTime": "ASC",
          "policy": "default",
          "refId": "A",
          "resultFormat": "time_series",
          "select": [
            [
              {
                "params": [
                  "value"
                ],
                "type": "field"
              },
              {
                "params": [],
                "type": "mean"
              }
            ]
          ],
          "tags": []
        }
      ],
      "title": "Primary Databases",
      "transformations": [
        {
          "id": "filterFieldsByName",
          "options": {
            "include": {
              "names": [
                "fqdn"
              ]
            }
          }
        }
      ],
      "type": "table"
    },
    {
      "datasource": {
        "type": "prometheus",
        "uid": "$PROMETHEUS_DS"
      },
      "fieldConfig": {
        "defaults": {
          "color": {
            "mode": "thresholds"
          },
          "custom": {
            "align": "auto",
            "cellOptions": {
              "type": "auto"
            },
            "inspect": false
          },
          "mappings": [],
          "thresholds": {
            "mode": "absolute",
            "steps": [
              {
                "color": "green"
              },
              {
                "color": "red",
                "value": 80
              }
            ]
          }
        },
        "overrides": [
          {
            "matcher": {
              "id": "byName",
              "options": "fqdn"
            },
            "properties": [
              {
                "id": "custom.width",
                "value": 434
              }
            ]
          },
          {
            "matcher": {
              "id": "byName",
              "options": "slot_name"
            },
            "properties": [
              {
                "id": "custom.width",
                "value": 441
              }
            ]
          }
        ]
      },
      "gridPos": {
        "h": 6,
        "w": 14,
        "x": 10,
        "y": 1
      },
      "id": 5,
      "options": {
        "cellHeight": "sm",
        "footer": {
          "countRows": false,
          "fields": "",
          "reducer": [
            "sum"
          ],
          "show": false
        },
        "showHeader": true,
        "sortBy": []
      },
      "pluginVersion": "11.6.1",
      "targets": [
        {
          "datasource": {
            "uid": "Global"
          },
          "dsType": "influxdb",
          "editorMode": "code",
          "expr": "pg_replication_slots_active{env=\"$environment\"}",
          "format": "table",
          "groupBy": [
            {
              "params": [
                "$__interval"
              ],
              "type": "time"
            },
            {
              "params": [
                "null"
              ],
              "type": "fill"
            }
          ],
          "instant": true,
          "intervalFactor": 2,
          "orderByTime": "ASC",
          "policy": "default",
          "refId": "A",
          "resultFormat": "time_series",
          "select": [
            [
              {
                "params": [
                  "value"
                ],
                "type": "field"
              },
              {
                "params": [],
                "type": "mean"
              }
            ]
          ],
          "tags": []
        }
      ],
      "title": "Replication Slots on Primaries",
      "transformations": [
        {
          "id": "filterFieldsByName",
          "options": {
            "include": {
              "names": [
                "fqdn",
                "slot_name",
                "Value"
              ]
            }
          }
        },
        {
          "id": "organize",
          "options": {
            "excludeByName": {},
            "includeByName": {},
            "indexByName": {},
            "renameByName": {
              "Value": "active",
              "fqdn": "primary",
              "slot_name": "slot name"
            }
          }
        }
      ],
      "type": "table"
    },
    {
      "collapsed": false,
      "gridPos": {
        "h": 1,
        "w": 24,
        "x": 0,
        "y": 7
      },
      "id": 10,
      "panels": [],
      "title": "Replica Info",
      "type": "row"
    },
    {
      "datasource": {
        "type": "prometheus",
        "uid": "$PROMETHEUS_DS"
      },
      "fieldConfig": {
        "defaults": {
          "color": {
            "mode": "thresholds"
          },
          "mappings": [
            {
              "options": {
                "match": "null",
                "result": {
                  "text": "N/A"
                }
              },
              "type": "special"
            }
          ],
          "thresholds": {
            "mode": "absolute",
            "steps": [
              {
                "color": "#bf1b00"
              },
              {
                "color": "#cca300",
                "value": 1
              },
              {
                "color": "#7eb26d",
                "value": 2
              }
            ]
          },
          "unit": "none"
        },
        "overrides": []
      },
      "gridPos": {
        "h": 6,
        "w": 4,
        "x": 0,
        "y": 8
      },
      "id": 2,
      "maxDataPoints": 100,
      "options": {
        "colorMode": "value",
        "graphMode": "area",
        "justifyMode": "auto",
        "orientation": "horizontal",
        "percentChangeColorMode": "standard",
        "reduceOptions": {
          "calcs": [
            "lastNotNull"
          ],
          "fields": "",
          "values": false
        },
        "showPercentChange": false,
        "textMode": "auto",
        "wideLayout": true
      },
      "pluginVersion": "11.6.1",
      "targets": [
        {
          "datasource": {
            "uid": "Global"
          },
          "dsType": "influxdb",
          "editorMode": "code",
          "expr": "count(pg_replication_is_replica{env=\"$environment\"}==1)",
          "format": "time_series",
          "groupBy": [
            {
              "params": [
                "$__interval"
              ],
              "type": "time"
            },
            {
              "params": [
                "null"
              ],
              "type": "fill"
            }
          ],
          "intervalFactor": 2,
          "orderByTime": "ASC",
          "policy": "default",
          "range": true,
          "refId": "A",
          "resultFormat": "time_series",
          "select": [
            [
              {
                "params": [
                  "value"
                ],
                "type": "field"
              },
              {
                "params": [],
                "type": "mean"
              }
            ]
          ],
          "tags": []
        }
      ],
      "title": "Replicas",
      "transparent": true,
      "type": "stat"
    },
    {
      "datasource": {
        "type": "prometheus",
        "uid": "$PROMETHEUS_DS"
      },
      "fieldConfig": {
        "defaults": {
          "color": {
            "mode": "thresholds"
          },
          "custom": {
            "align": "auto",
            "cellOptions": {
              "type": "auto"
            },
            "inspect": false
          },
          "mappings": [],
          "thresholds": {
            "mode": "absolute",
            "steps": [
              {
                "color": "green"
              },
              {
                "color": "red",
                "value": 80
              }
            ]
          }
        },
        "overrides": []
      },
      "gridPos": {
        "h": 6,
        "w": 6,
        "x": 4,
        "y": 8
      },
      "id": 4,
      "options": {
        "cellHeight": "sm",
        "footer": {
          "countRows": false,
          "fields": "",
          "reducer": [
            "sum"
          ],
          "show": false
        },
        "showHeader": true
      },
      "pluginVersion": "11.6.1",
      "targets": [
        {
          "datasource": {
            "uid": "Global"
          },
          "dsType": "influxdb",
          "editorMode": "code",
          "expr": "pg_replication_is_replica{env=\"$environment\"}==1",
          "format": "table",
          "groupBy": [
            {
              "params": [
                "$__interval"
              ],
              "type": "time"
            },
            {
              "params": [
                "null"
              ],
              "type": "fill"
            }
          ],
          "instant": true,
          "intervalFactor": 2,
          "legendFormat": "",
          "orderByTime": "ASC",
          "policy": "default",
          "refId": "A",
          "resultFormat": "time_series",
          "select": [
            [
              {
                "params": [
                  "value"
                ],
                "type": "field"
              },
              {
                "params": [],
                "type": "mean"
              }
            ]
          ],
          "tags": []
        }
      ],
      "title": "Replica Databases",
      "transformations": [
        {
          "id": "filterFieldsByName",
          "options": {
            "include": {
              "names": [
                "fqdn"
              ]
            }
          }
        }
      ],
      "type": "table"
    },
    {
      "datasource": {
        "type": "prometheus",
        "uid": "$PROMETHEUS_DS"
      },
      "fieldConfig": {
        "defaults": {
          "color": {
            "mode": "thresholds"
          },
          "custom": {
            "align": "auto",
            "cellOptions": {
              "type": "auto"
            },
            "inspect": false
          },
          "mappings": [],
          "thresholds": {
            "mode": "absolute",
            "steps": [
              {
                "color": "green"
              },
              {
                "color": "red",
                "value": 80
              }
            ]
          }
        },
        "overrides": [
          {
            "matcher": {
              "id": "byName",
              "options": "replica"
            },
            "properties": [
              {
                "id": "custom.width",
                "value": 416
              }
            ]
          },
          {
            "matcher": {
              "id": "byName",
              "options": "slot name"
            },
            "properties": [
              {
                "id": "custom.width",
                "value": 422
              }
            ]
          }
        ]
      },
      "gridPos": {
        "h": 6,
        "w": 14,
        "x": 10,
        "y": 8
      },
      "id": 6,
      "options": {
        "cellHeight": "sm",
        "footer": {
          "countRows": false,
          "fields": "",
          "reducer": [
            "sum"
          ],
          "show": false
        },
        "showHeader": true,
        "sortBy": []
      },
      "pluginVersion": "11.6.1",
      "targets": [
        {
          "datasource": {
            "type": "prometheus",
            "uid": "$PROMETHEUS_DS"
          },
          "dsType": "influxdb",
          "expr": "pg_stat_wal_receiver_status{env=\"$environment\"}",
          "format": "table",
          "groupBy": [
            {
              "params": [
                "$__interval"
              ],
              "type": "time"
            },
            {
              "params": [
                "null"
              ],
              "type": "fill"
            }
          ],
          "instant": true,
          "intervalFactor": 2,
          "orderByTime": "ASC",
          "policy": "default",
          "refId": "A",
          "resultFormat": "time_series",
          "select": [
            [
              {
                "params": [
                  "value"
                ],
                "type": "field"
              },
              {
                "params": [],
                "type": "mean"
              }
            ]
          ],
          "tags": []
        }
      ],
      "title": "Replica WAL Receiver Status",
      "transformations": [
        {
          "id": "filterFieldsByName",
          "options": {
            "include": {
              "names": [
                "fqdn",
                "slot_name",
                "upstream_host",
                "Value"
              ]
            }
          }
        },
        {
          "id": "organize",
          "options": {
            "excludeByName": {},
            "includeByName": {},
            "indexByName": {},
            "renameByName": {
              "Value": "status",
              "fqdn": "replica",
              "slot_name": "slot name",
              "upstream_host": "upstream leader"
            }
          }
        }
      ],
      "type": "table"
    },
    {
      "datasource": {
        "type": "prometheus",
        "uid": "$PROMETHEUS_DS"
      },
      "fieldConfig": {
        "defaults": {
          "color": {
            "mode": "palette-classic"
          },
          "custom": {
            "axisBorderShow": false,
            "axisCenteredZero": false,
            "axisColorMode": "text",
            "axisLabel": "",
            "axisPlacement": "auto",
            "barAlignment": 0,
            "barWidthFactor": 0.6,
            "drawStyle": "line",
            "fillOpacity": 0,
            "gradientMode": "none",
            "hideFrom": {
              "legend": false,
              "tooltip": false,
              "viz": false
            },
            "insertNulls": false,
            "lineInterpolation": "linear",
            "lineWidth": 1,
            "pointSize": 5,
            "scaleDistribution": {
              "type": "linear"
            },
            "showPoints": "auto",
            "spanNulls": false,
            "stacking": {
              "group": "A",
              "mode": "none"
            },
            "thresholdsStyle": {
              "mode": "off"
            }
          },
          "mappings": [],
          "thresholds": {
            "mode": "absolute",
            "steps": [
              {
                "color": "green"
              },
              {
                "color": "red",
                "value": 80
              }
            ]
          }
        },
        "overrides": []
      },
      "gridPos": {
        "h": 9,
        "w": 24,
        "x": 0,
        "y": 14
      },
      "id": 14,
      "options": {
        "legend": {
          "calcs": [],
          "displayMode": "list",
          "placement": "bottom",
          "showLegend": true
        },
        "tooltip": {
          "hideZeros": false,
          "mode": "single",
          "sort": "none"
        }
      },
      "pluginVersion": "11.6.1",
      "targets": [
        {
          "datasource": {
            "type": "prometheus",
            "uid": "$PROMETHEUS_DS"
          },
          "expr": "pg_replication_is_replica{env=\"$environment\"}==0",
          "interval": "",
          "legendFormat": "Primary database ({{fqdn}})",
          "refId": "A"
        }
      ],
      "title": "Primary database",
      "type": "timeseries"
    },
    {
      "collapsed": false,
      "gridPos": {
        "h": 1,
        "w": 24,
        "x": 0,
        "y": 23
      },
      "id": 11,
      "panels": [],
      "title": "Replication Topology",
      "type": "row"
    },
    {
      "datasource": {
        "type": "prometheus",
        "uid": "$PROMETHEUS_DS"
      },
      "fieldConfig": {
        "defaults": {
          "color": {
            "mode": "thresholds"
          },
          "custom": {
            "align": "auto",
            "cellOptions": {
              "type": "auto"
            },
            "inspect": false
          },
          "mappings": [],
          "thresholds": {
            "mode": "absolute",
            "steps": [
              {
                "color": "green"
              },
              {
                "color": "red",
                "value": 80
              }
            ]
          }
        },
        "overrides": [
          {
            "matcher": {
              "id": "byName",
              "options": "replica"
            },
            "properties": [
              {
                "id": "custom.width",
                "value": 418
              }
            ]
          },
          {
            "matcher": {
              "id": "byName",
              "options": "slot name"
            },
            "properties": [
              {
                "id": "custom.width",
                "value": 420
              }
            ]
          }
        ]
      },
      "gridPos": {
        "h": 7,
        "w": 24,
        "x": 0,
        "y": 24
      },
      "id": 7,
      "options": {
        "cellHeight": "sm",
        "footer": {
          "countRows": false,
          "fields": "",
          "reducer": [
            "sum"
          ],
          "show": false
        },
        "showHeader": true,
        "sortBy": []
      },
      "pluginVersion": "11.6.1",
      "targets": [
        {
          "datasource": {
            "type": "prometheus",
            "uid": "$PROMETHEUS_DS"
          },
          "dsType": "influxdb",
          "expr": "pg_stat_wal_receiver_status{env=\"$environment\"} or on (slot_name,upstream_host) label_replace(pg_replication_slots_active{env=\"$environment\"},\"upstream_host\",\"$1\",\"fqdn\",\"(.*)\") ",
          "format": "table",
          "groupBy": [
            {
              "params": [
                "$__interval"
              ],
              "type": "time"
            },
            {
              "params": [
                "null"
              ],
              "type": "fill"
            }
          ],
          "instant": true,
          "intervalFactor": 2,
          "orderByTime": "ASC",
          "policy": "default",
          "refId": "A",
          "resultFormat": "time_series",
          "select": [
            [
              {
                "params": [
                  "value"
                ],
                "type": "field"
              },
              {
                "params": [],
                "type": "mean"
              }
            ]
          ],
          "tags": []
        }
      ],
      "title": "Combined Primary/Replica Slot/Receiver",
      "transformations": [
        {
          "id": "filterFieldsByName",
          "options": {
            "include": {
              "names": [
                "fqdn",
                "slot_name",
                "upstream_host",
                "Value"
              ]
            }
          }
        },
        {
          "id": "organize",
          "options": {
            "excludeByName": {},
            "includeByName": {},
            "indexByName": {},
            "renameByName": {
              "Value": "receiver status",
              "fqdn": "replica",
              "slot_name": "slot name",
              "upstream_host": "leader"
            }
          }
        }
      ],
      "type": "table"
    },
    {
      "collapsed": false,
      "gridPos": {
        "h": 1,
        "w": 24,
        "x": 0,
        "y": 31
      },
      "id": 12,
      "panels": [],
      "title": "Dashboard Row",
      "type": "row"
    },
    {
      "fieldConfig": {
        "defaults": {},
        "overrides": []
      },
      "gridPos": {
        "h": 13,
        "w": 24,
        "x": 0,
        "y": 32
      },
      "id": 8,
      "options": {
        "code": {
          "language": "plaintext",
          "showLineNumbers": false,
          "showMiniMap": false
        },
        "content": "<iframe  frameBorder=\"0\" hspace=\"0\" vspace=\"0\" marginheight=\"0\" marginwidth=\"0\" seamless=seamless border=0 width=\"100%\" height=\"500\" src=\"https://prometheus.gitlab.com/consoles/topology.html?environment=$environment\">\n</iframe>\n(Disable Ad-Blocker and/or PrivacyBadger if this doesn't appear)",
        "mode": "html"
      },
      "pluginVersion": "11.6.1",
      "title": "Replication Topology",
      "transparent": true,
      "type": "text"
    }
  ],
  "preload": false,
  "refresh": "",
  "schemaVersion": 41,
  "tags": [],
  "templating": {
    "list": [
      {
        "current": {
          "text": "Mimir - Gitlab Gprd",
          "value": "mimir-gitlab-gprd"
        },
        "name": "PROMETHEUS_DS",
        "options": [],
        "query": "prometheus",
        "refresh": 1,
        "regex": "",
        "type": "datasource"
      },
      {
        "current": {
          "text": "gprd",
          "value": "gprd"
        },
        "includeAll": false,
        "label": "Environment",
        "name": "environment",
        "options": [
          {
            "selected": true,
            "text": "gprd",
            "value": "gprd"
          },
          {
            "selected": false,
            "text": "gstg",
            "value": "gstg"
          }
        ],
        "query": "gprd,gstg",
        "type": "custom"
      }
    ]
  },
  "time": {
    "from": "now-6h",
    "to": "now"
  },
  "timepicker": {
    "refresh_intervals": [
      "5m",
      "15m",
      "30m",
      "1h",
      "2h",
      "1d"
    ]
  },
  "timezone": "",
  "title": "PostgreSQL Replication Overview",
  "uid": "cemft60lqicxsf",
  "version": 6
}
